wikipedia_scraper_in
