Metadata-Version: 2.1
Name: wikipedia-scraper-in
Version: 1.0.1
Summary: A python library to Scrape Wikipedia.
Home-page: UNKNOWN
Author: DataKund
Author-email: datakund@gmail.com
License: Apache License 2.0
Keywords: wikipedia python bot_studio automation product scraper city service
Platform: UNKNOWN
License-File: LICENSE
